wunplots/__init__.py
wunplots/plotting.py
wunplots/utils.py
wunplots-0.1.1.dist-info/LICENSE.txt
wunplots-0.1.1.dist-info/METADATA
wunplots-0.1.1.dist-info/WHEEL
wunplots-0.1.1.dist-info/RECORD
