Metadata-Version: 2.1
Name: wunplots
Version: 0.1.1
Summary: Plotting utilities
License: LICENSE.txt
Author: Philippe Lacroix-Ouellette
Author-email: philippe.lacroix.ouellette@gmail.com
Requires-Python: >=3.9,<4.0
Classifier: License :: Other/Proprietary License
Classifier: Programming Language :: Python :: 3
Classifier: Programming Language :: Python :: 3.9
Classifier: Programming Language :: Python :: 3.10
Classifier: Programming Language :: Python :: 3.11
Classifier: Programming Language :: Python :: 3.12
Requires-Dist: cycler (>=0.12.1,<0.13.0)
Requires-Dist: matplotlib (>=3.8.0,<4.0.0)
Requires-Dist: numpy (>=1.26.3,<2.0.0)
Requires-Dist: wuncolors (==0.1.1)
